cscan/__init__.py
cscan/cli.py
cscan-0.1.1.dist-info/licenses/LICENSE
cscan-0.1.1.dist-info/METADATA
cscan-0.1.1.dist-info/WHEEL
cscan-0.1.1.dist-info/entry_points.txt
cscan-0.1.1.dist-info/top_level.txt
cscan-0.1.1.dist-info/RECORD
