Metadata-Version: 2.4
Name: cscan
Version: 0.1.1
Summary: A simple C vuln cli scanner
Home-page: https://github.com/edoggy777/cscan
Author: Evan Kirtz
Author-email: kirtzevan@gmail.com
License: MIT
Classifier: Programming Language :: Python :: 3
Classifier: License :: OSI Approved :: MIT License
Classifier: Operating System :: OS Independent
Requires-Python: >=3.8
License-File: LICENSE
Dynamic: license-file
